weathercontest/__init__.py
weathercontest/client.py
weathercontest-0.0.7.dist-info/LICENSE
weathercontest-0.0.7.dist-info/METADATA
weathercontest-0.0.7.dist-info/WHEEL
weathercontest-0.0.7.dist-info/top_level.txt
weathercontest-0.0.7.dist-info/RECORD
