Metadata-Version: 2.1
Name: weathercontest
Version: 0.0.7
Summary: weathercontest
Author-email: Comus Leong <comus.leong@gmail.com>
Classifier: Programming Language :: Python :: 3
Classifier: License :: OSI Approved :: MIT License
Classifier: Operating System :: OS Independent
Requires-Python: >=3.7
License-File: LICENSE
Requires-Dist: requests
